qiskit_leaky_scheduling/HSLU_Logo_small.png
qiskit_leaky_scheduling/__init__.py
qiskit_leaky_scheduling/decoder.py
qiskit_leaky_scheduling/leaky_scheduling_plugin.py
qiskit_leaky_scheduling-0.2.3.dist-info/licenses/LICENSE
qiskit_leaky_scheduling-0.2.3.dist-info/METADATA
qiskit_leaky_scheduling-0.2.3.dist-info/WHEEL
qiskit_leaky_scheduling-0.2.3.dist-info/entry_points.txt
qiskit_leaky_scheduling-0.2.3.dist-info/top_level.txt
qiskit_leaky_scheduling-0.2.3.dist-info/RECORD
