Metadata-Version: 2.4
Name: qiskit-leaky-scheduling
Version: 0.2.3
Summary: A transpilation plugin for Qiskit with a modified scheduling stage that encodes (classical) information modifying the angles of RZGates without leading to changes in the computation results
Author-email: Iyán Méndez Veiga <me@iyanmv.com>
License: MIT License
Project-URL: homepage, https://github.com/iyanmv/qiskit-leaky-scheduling
Project-URL: source, https://github.com/iyanmv/qiskit-leaky-scheduling
Project-URL: issues, https://github.com/iyanmv/qiskit-leaky-scheduling/issues
Project-URL: arXiv Paper, https://arxiv.org/abs/2510.02251
Requires-Python: >=3.10
License-File: LICENSE
Requires-Dist: qiskit<2.4,>=1.0
Requires-Dist: qiskit-ibm-runtime>=0.25.0
Dynamic: license-file
